oip_dataset_client/HttpClient.py
oip_dataset_client/ParallelZipper.py
oip_dataset_client/ServerConf.py
oip_dataset_client/ServerFacade.py
oip_dataset_client/__init__.py
oip_dataset_client/dataset.py
oip_dataset_client/logger.py
oip_dataset_client/schema.py
oip_dataset_client/utils.py
oip_dataset_client/version.py
oip_dataset_client/Storage/AwsProvider.py
oip_dataset_client/Storage/AzureProvider.py
oip_dataset_client/Storage/GcpProvider.py
oip_dataset_client/Storage/MinioProvider.py
oip_dataset_client/Storage/StorageManager.py
oip_dataset_client/Storage/StorageProvider.py
oip_dataset_client/Storage/__init__.py
oip_dataset_client/cli/__init__.py
oip_dataset_client/cli/config/__init__.py
oip_dataset_client/cli/config/__main__.py
oip_dataset_client/examples/__init__.py
oip_dataset_client/examples/create_dataset.py
oip_dataset_client/examples/create_dataset_with_multiple_parents.py
oip_dataset_client/examples/download_external_dataset.py
oip_dataset_client/examples/download_internal_dataset.py
oip_dataset_client-0.5.0.dist-info/METADATA
oip_dataset_client-0.5.0.dist-info/WHEEL
oip_dataset_client-0.5.0.dist-info/entry_points.txt
oip_dataset_client-0.5.0.dist-info/top_level.txt
oip_dataset_client-0.5.0.dist-info/RECORD
