Metadata-Version: 2.4
Name: oip-dataset-client
Version: 0.5.0
Summary: This is the API client of Open Innovation MLOps Platform - Dataset
Author: Rachid Belmeskine
Author-email: rachid.belmeskine@gmail.com
License: PRIVATE LICENSE
Requires-Python: >=3.7
Requires-Dist: typeguard==2.13.3
Requires-Dist: requests>=2.27.1
Requires-Dist: six==1.16.0
Requires-Dist: psutil==5.9.8
Requires-Dist: tqdm>=4.66.1
Requires-Dist: boto3>=1.26.20
Requires-Dist: PyYAML==6.0.1
Requires-Dist: attrs==23.2.0
Requires-Dist: python-dotenv==1.0.1
Requires-Dist: pandas==2.3.1
Dynamic: author
Dynamic: author-email
Dynamic: description
Dynamic: description-content-type
Dynamic: license
Dynamic: requires-dist
Dynamic: requires-python
Dynamic: summary
